finalProject/2_8/mux2x1.v
`timescale 10ns / 1ns 
module mux2x1(output dout, input sel, input [1:0] din);
    bufif1 b2(dout, din[1], sel);
    bufif0 b1(dout, din[0], sel);
endmodule

finalProject/2_8/comb_str.v
`include "mux2x1.v"
`timescale 10ns / 1ns 
module comb_str(output y, input sel, A, B, C, D);
    wire u1v, u2v;

    nand #(3) u1(u1v, A, B);
    nand #(4) u2(u2v, C, D);

    mux2x1 mux(.dout(y), .sel(sel), .din({u2v, u1v}));

endmodule

finalProject/2_8/tb_comb_str.v
`include "comb_str.v"
`timescale 10ns / 1ns 
module tb_comb_str();
    reg p_A, p_B, p_C, p_D;
    reg p_sel;
    wire p_y;

    comb_str comb(.y(p_y), .sel(p_sel), .A(p_A), .B(p_B), .C(p_C), .D(p_D));

    initial
    begin
        {p_A, p_B, p_C, p_D} = 4'bx;
        p_sel = 1'b0;
        forever 
        begin
            #10;
            {p_A, p_B, p_C, p_D} = {$random} % 256;
            p_sel = {$random}%2;
        end
    end

    initial
    begin
        $monitor($time, "ABCD=%b%b%b%b, sel = %b, y = %b",
                        p_A, p_B, p_C, p_D, p_sel, p_y);
        $dumpfile("tb_comb_str.vcd");
        $dumpvars(0, tb_comb_str);
        #120 $finish;
    end
endmodule

finalProject/2_8/tb_comb_str.vcd
$date
	Thu Nov 21 23:36:10 2019
$end
$version
	Icarus Verilog
$end
$timescale
	1ns
$end
$scope module tb_comb_str $end
$var wire 1 ! p_y $end
$var reg 1 " p_A $end
$var reg 1 # p_B $end
$var reg 1 $ p_C $end
$var reg 1 % p_D $end
$var reg 1 & p_sel $end
$scope module comb $end
$var wire 1 " A $end
$var wire 1 # B $end
$var wire 1 $ C $end
$var wire 1 % D $end
$var wire 1 & sel $end
$var wire 1 ' u1v $end
$var wire 1 ( u2v $end
$var wire 1 ! y $end
$scope module mux $end
$var wire 2 ) din [1:0] $end
$var wire 1 ! dout $end
$var wire 1 & sel $end
$upscope $end
$upscope $end
$upscope $end
$enddefinitions $end
#0
$dumpvars
bx )
x(
x'
0&
x%
x$
x#
x"
x!
$end
#100
x!
1&
0"
1#
0$
0%
#130
bx1 )
1'
#140
1!
b11 )
1(
#200
1"
0#
1%
#300
1#
#330
b10 )
0'
#400
0!
0&
0"
#430
1!
b11 )
1'
#500
1!
1&
0#
#600
1#
1$
0%
#700
0&
1"
0$
1%
#730
0!
b10 )
0'
#800
0#
#830
1!
b11 )
1'
#900
0"
1#
#1000
1!
1&
#1100
0#
1$
0%
