dailyExercise/adder/fwd_adder_4b.v
module fwd_adder_4b(output cout, output [3:0] sum, input [3:0] a,b, input cin);
    wire [3:0] gen, pro;
    genvar k;
    generate for(k = 0; k < 4;k = k+1)
    begin :LOOP
        assign gen[k] = a[k] & b[k];
        assign pro[k] = a[k] ^ b[k];
    end
    endgenerate

    wire g3,g2,g1,g0, p3,p2,p1,p0,c3,c2,c1,c0;

    assign  {g3,g2,g1,g0} = gen,
            {p3,p2,p1,p0} = pro;

    assign  c0 = g0 | (p0 & cin),
            c1 = g1 | (p1 & g0) | (p1 & p0 & cin),
            c2 = g2 | (p2 & g1) | (p2 & p1 & g0) | (p2 & p1 & p0 & cin ),
            c3 = g3 | (p3 & g2) | (p3 & p2 & g1) | (p3 & p2 & p1 & g0) | (p3 & p2 & p1 & p0 & cin);

    assign  sum = {p3, p2, p1, p0} ^ {c2, c1, c0, cin};
    assign  cout = c3;
endmodule

dailyExercise/adder/fwd_adder_8b.v
`include "fwd_adder_4b.v"
module fwd_adder_8b(output cout, output [7:0] sum, input [7:0] a,b, input cin);
    wire c3,c7;
    wire [3:0] s0,s1,a0,a1,b0,b1;

    assign a0 = a[3:0], a1 = a[7:4], b0 = b[3:0], b1 = b[7:4];

    fwd_adder_4b add1(.cout(c3), .sum(s0), .a(a0), .b(b0), .cin(cin));
    fwd_adder_4b add2(.cout(c7), .sum(s1), .a(a1), .b(b1), .cin(c3) );

    assign {cout, sum} = {c7, s1, s0};
endmodule

dailyExercise/adder/top.v
`include "fwd_adder_8b.v"
`timescale 1ns / 100ps
// 加法器
module top;
    reg [7:0] num1, num2;
    reg cain;
    wire [7:0] sumup; 
    wire caout;

    // fulladd adder(.cout(caout), .sum(sumup), .a(num1), .b(num2), .cin(cain));
    // fwd_adder_4b adder(.sum(sumup), .cout(caout), .a(num1), .b(num2), .cin(cain));
    fwd_adder_8b adder(.sum(sumup), .cout(caout), .a(num1), .b(num2), .cin(cain));
    integer k;

    initial
    begin
        cain = 1'b0;
        {num1,num2} = 16'b0;
        for(k = 0; k < 10; k = k + 1)
        begin
            #5 ;
            {num1,num2} = {$random} % 65535;
            cain = {$random} % 2;
        end
    end

    initial
        $monitor($time, "\t%b + %b + %b = %b%b",
                        adder.a, adder.b, adder.cin, adder.cout, adder.sum);

    initial
    begin
        $dumpfile("top.vcd");
        $dumpvars(0, top);
    end

endmodule

dailyExercise/adder/top.vcd
$date
	Mon Nov 18 20:32:09 2019
$end
$version
	Icarus Verilog
$end
$timescale
	100ps
$end
$scope module top $end
$var wire 8 ! sumup [7:0] $end
$var wire 1 " caout $end
$var reg 1 # cain $end
$var reg 8 $ num1 [7:0] $end
$var reg 8 % num2 [7:0] $end
$var integer 32 & k [31:0] $end
$scope module adder $end
$var wire 8 ' a [7:0] $end
$var wire 8 ( b [7:0] $end
$var wire 1 # cin $end
$var wire 8 ) sum [7:0] $end
$var wire 4 * s1 [3:0] $end
$var wire 4 + s0 [3:0] $end
$var wire 1 " cout $end
$var wire 1 , c7 $end
$var wire 1 - c3 $end
$var wire 4 . b1 [3:0] $end
$var wire 4 / b0 [3:0] $end
$var wire 4 0 a1 [3:0] $end
$var wire 4 1 a0 [3:0] $end
$scope module add1 $end
$var wire 4 2 a [3:0] $end
$var wire 4 3 b [3:0] $end
$var wire 1 4 c0 $end
$var wire 1 5 c1 $end
$var wire 1 6 c2 $end
$var wire 1 7 c3 $end
$var wire 1 # cin $end
$var wire 1 - cout $end
$var wire 4 8 sum [3:0] $end
$var wire 4 9 pro [3:0] $end
$var wire 1 : p3 $end
$var wire 1 ; p2 $end
$var wire 1 < p1 $end
$var wire 1 = p0 $end
$var wire 4 > gen [3:0] $end
$var wire 1 ? g3 $end
$var wire 1 @ g2 $end
$var wire 1 A g1 $end
$var wire 1 B g0 $end
$scope begin LOOP[0] $end
$upscope $end
$scope begin LOOP[1] $end
$upscope $end
$scope begin LOOP[2] $end
$upscope $end
$scope begin LOOP[3] $end
$upscope $end
$upscope $end
$scope module add2 $end
$var wire 4 C a [3:0] $end
$var wire 4 D b [3:0] $end
$var wire 1 E c0 $end
$var wire 1 F c1 $end
$var wire 1 G c2 $end
$var wire 1 H c3 $end
$var wire 1 - cin $end
$var wire 1 , cout $end
$var wire 4 I sum [3:0] $end
$var wire 4 J pro [3:0] $end
$var wire 1 K p3 $end
$var wire 1 L p2 $end
$var wire 1 M p1 $end
$var wire 1 N p0 $end
$var wire 4 O gen [3:0] $end
$var wire 1 P g3 $end
$var wire 1 Q g2 $end
$var wire 1 R g1 $end
$var wire 1 S g0 $end
$scope begin LOOP[0] $end
$upscope $end
$scope begin LOOP[1] $end
$upscope $end
$scope begin LOOP[2] $end
$upscope $end
$scope begin LOOP[3] $end
$upscope $end
$upscope $end
$upscope $end
$upscope $end
$enddefinitions $end
#0
$dumpvars
0S
0R
0Q
0P
b0 O
0N
0M
0L
0K
b0 J
b0 I
0H
0G
0F
0E
b0 D
b0 C
0B
0A
0@
0?
b0 >
0=
0<
0;
0:
b0 9
b0 8
07
06
05
04
b0 3
b0 2
b0 1
b0 0
b0 /
b0 .
0-
0,
b0 +
b0 *
b0 )
b0 (
b0 '
b0 &
b0 %
b0 $
0#
0"
b0 !
$end
#50
1E
1F
1G
1-
17
16
15
14
b1000 *
b1000 I
1<
1;
1L
1B
1:
1N
1M
b1 >
b1110 9
b111 J
b10000001 !
b10000001 )
b1 +
b1 8
b111 1
b111 2
b100 0
b100 C
b1001 /
b1001 3
b11 .
b11 D
b1 &
1#
b1000111 $
b1000111 '
b111001 %
b111001 (
#100
0G
0F
b11101001 !
b11101001 )
04
b1001 +
b1001 8
b1110 *
b1110 I
1?
0:
0B
1A
0<
0M
1K
b1010 >
b100 9
b1101 J
b1010 1
b1010 2
b101 0
b101 C
b1110 /
b1110 3
b1000 .
b1000 D
b10 &
b1011010 $
b1011010 '
b10001110 %
b10001110 (
#150
1"
1,
1H
0-
07
14
0E
b1001000 !
b1001000 )
b1000 +
b1000 8
b100 *
b100 I
1=
0A
1<
0N
1P
0K
0?
b111 9
b1000 O
b100 J
b0 >
b1 1
b1 2
b1000 0
b1000 C
b110 /
b110 3
b1100 .
b1100 D
b11 &
b10000001 $
b10000001 '
b11000110 %
b11000110 (
#200
0"
0,
0H
1F
b101 *
b101 I
1N
1:
1R
0L
0P
b1111 9
b1 J
b10 O
04
05
06
b1011111 !
b1011111 )
b1111 +
b1111 8
b111 1
b111 2
b11 0
b11 C
b1000 /
b1000 3
b10 .
b10 D
b100 &
0#
b110111 $
b110111 '
b101000 %
b101000 (
#250
1"
1,
1H
1G
0E
0:
1Q
1P
b1101 *
b1101 I
b111 9
b1110 O
14
15
16
0-
07
b11011000 !
b11011000 )
b1000 +
b1000 8
b11 1
b11 2
b1110 0
b1110 C
b100 /
b100 3
b1111 .
b1111 D
b101 &
1#
b11100011 $
b11100011 '
b11110100 %
b11110100 (
#300
1E
0"
0,
0H
1-
17
06
05
0G
04
1F
b11000111 !
b11000111 )
b111 +
b111 8
b1100 *
b1100 I
0=
0P
1K
1?
0R
1M
0Q
b110 9
b1000 >
b1011 J
b0 O
b1100 1
b1100 2
b10 0
b10 C
b1010 /
b1010 3
b1001 .
b1001 D
b110 &
b101100 $
b101100 '
b10011010 %
b10011010 (
#350
1"
1,
1H
0-
07
0F
1G
0E
b1000 *
b1000 I
0M
1P
0K
1=
0?
1:
0N
1Q
b0 >
b1111 9
b0 J
b1100 O
b10001111 !
b10001111 )
b1111 +
b1111 8
b1110 1
b1110 2
b1100 0
b1100 C
b1 /
b1 3
b1100 .
b1100 D
b111 &
0#
b11001110 $
b11001110 '
b11000001 %
b11000001 (
#400
16
15
b1011101 !
b1011101 )
1F
b1101 +
b1101 8
b101 *
b101 I
0:
0P
1K
1A
0<
1@
0;
1N
1R
b110 >
b1 9
b1001 J
b110 O
b110 1
b110 2
b110 0
b110 C
b111 /
b111 3
b1111 .
b1111 D
b1000 &
b1100110 $
b1100110 '
b11110111 %
b11110111 (
#450
1E
1-
17
b100100 !
b100100 )
14
b100 +
b100 8
b10 *
b10 I
1B
0=
0A
1<
1:
0Q
1L
b101 >
b1010 9
b10 O
b1101 J
b111 1
b111 2
b1101 /
b1101 3
b1011 .
b1011 D
b1001 &
b1100111 $
b1100111 '
b10111101 %
b10111101 (
#500
b0 *
b0 I
0B
1=
0@
1;
0R
1M
b0 >
b1111 9
b0 O
b1111 J
b0 !
b0 )
b0 +
b0 8
b1010 1
b1010 2
b101 /
b101 3
b1001 .
b1001 D
b1010 &
1#
b1101010 $
b1101010 '
b10010101 %
b10010101 (
