finalProject/2_9/LFSR.v
module LFSR(output reg [1:26] q,
            input clk,
            input rst_n,
            input load,
            input [1:26] din
            );
    always @(posedge clk) begin
        if( ~rst_n )
            q <= 8'b0;
        else begin
            if(load)
                q <= (|din) ? din : 8'b0000_0001;
            else begin
                if (q == 8'b0)
                    q <= 8'b0000_0001;
                else begin
                    {q[26], q[25], q[24], q[23]} <= {q[25], q[24], q[23], q[22]};
                    {q[22], q[21], q[20], q[19]} <= {q[21], q[20], q[19], q[18]};
                    {q[18], q[17], q[16], q[15]} <= {q[17], q[16], q[15], q[14]};
                    {q[14], q[13], q[12], q[11]} <= {q[13], q[12], q[11], q[10]};
                    q[10] <= q[9];
                    q[9] <= q[8] ^ q[26];
                    q[8] <= q[7] ^ q[26];
                    q[7] <= q[6];
                    {q[6], q[5], q[4], q[3]} <= {q[5], q[4], q[3], q[2]};
                    q[2] <= q[1] ^ q[26];
                    q[1] <= q[26];
                end
            end
        end
    end
endmodule

finalProject/2_9/tb_LFSR.v
`include "LFSR.v"
`timescale 10ns / 1ns
module tb_LFSR();
    reg p_clk;
    reg p_rst_n;
    reg p_load;
    reg [1:26] p_din;
    wire [1:26] p_q;

    LFSR sr(.q(p_q), .clk(p_clk), .rst_n(p_rst_n), .load(p_load), .din(p_din));

    initial 
    begin
        p_clk = 1'b0;
        forever #5 p_clk = ~p_clk;
    end

    initial 
    begin
        p_rst_n = 1'b0;
        p_din = {$random} % (1 << 26);
        #4 p_rst_n = 1'b1;
        #4 p_load = 1'b1;
        #8 p_load = 1'b0;
        #200 $finish; 
    end

    initial
    begin
        $monitor($time, " num is %b",p_q);
        $dumpfile("tb_LFSR.vcd");
        $dumpvars(0, tb_LFSR);
    end
endmodule

finalProject/2_9/tb_LFSR.vcd
$date
	Fri Nov 22 00:01:23 2019
$end
$version
	Icarus Verilog
$end
$timescale
	1ns
$end
$scope module tb_LFSR $end
$var wire 26 ! p_q [1:26] $end
$var reg 1 " p_clk $end
$var reg 26 # p_din [1:26] $end
$var reg 1 $ p_load $end
$var reg 1 % p_rst_n $end
$scope module sr $end
$var wire 1 " clk $end
$var wire 26 & din [1:26] $end
$var wire 1 $ load $end
$var wire 1 % rst_n $end
$var reg 26 ' q [1:26] $end
$upscope $end
$upscope $end
$enddefinitions $end
#0
$dumpvars
bx '
b10000101010011010100100100 &
0%
x$
b10000101010011010100100100 #
0"
bx !
$end
#40
1%
#50
1"
#80
1$
#100
0"
#150
b10000101010011010100100100 !
b10000101010011010100100100 '
1"
#160
0$
#200
0"
#250
b1000010101001101010010010 !
b1000010101001101010010010 '
1"
#300
0"
#350
b100001010100110101001001 !
b100001010100110101001001 '
1"
#400
0"
#450
b11010001001010011010100100 !
b11010001001010011010100100 '
1"
#500
0"
#550
b1101000100101001101010010 !
b1101000100101001101010010 '
1"
#600
0"
#650
b110100010010100110101001 !
b110100010010100110101001 '
1"
#700
0"
#750
b11011011101001010011010100 !
b11011011101001010011010100 '
1"
#800
0"
#850
b1101101110100101001101010 !
b1101101110100101001101010 '
1"
#900
0"
#950
b110110111010010100110101 !
b110110111010010100110101 '
1"
#1000
0"
#1050
b11011010111101001010011010 !
b11011010111101001010011010 '
1"
#1100
0"
#1150
b1101101011110100101001101 !
b1101101011110100101001101 '
1"
#1200
0"
#1250
b11110111001111010010100110 !
b11110111001111010010100110 '
1"
#1300
0"
#1350
b1111011100111101001010011 !
b1111011100111101001010011 '
1"
#1400
0"
#1450
b11111100010011110100101001 !
b11111100010011110100101001 '
1"
#1500
0"
#1550
b10111111101001111010010100 !
b10111111101001111010010100 '
1"
#1600
0"
#1650
b1011111110100111101001010 !
b1011111110100111101001010 '
1"
#1700
0"
#1750
b101111111010011110100101 !
b101111111010011110100101 '
1"
#1800
0"
#1850
b11010110011101001111010010 !
b11010110011101001111010010 '
1"
#1900
0"
#1950
b1101011001110100111101001 !
b1101011001110100111101001 '
1"
#2000
0"
#2050
b11110100000111010011110100 !
b11110100000111010011110100 '
1"
#2100
0"
#2150
b1111010000011101001111010 !
b1111010000011101001111010 '
1"
