finalProject/2_13/shift_counter.v
module shift_counter(output reg [7:0] count, input clk, reset);
    reg [9:0] internal;
    reg dir;
    always @(posedge clk) begin
        if(reset) begin
            internal <= 10'b1;
            dir <= 1'b1;
        end
        else begin
            if(dir) begin   
                if(internal == 10'b10_0000_0000)
                    dir <= 1'b0;
                else
                    internal <= internal << 1;
            end
            else begin
                if(internal == 10'b00_0000_0100)
                    dir <= 1'b1;
                else
                    internal <= internal >> 1;
            end
            if(internal <= 10'b00_0000_0100)
                count <= 8'b0000_0001;
            else
                count <= internal[9:2];
        end
    end
endmodule

finalProject/2_13/tb_shift_counter.v
`include "shift_counter.v"
`timescale 10ns / 1ns
module tb_shift_counter();
    wire [7:0] p_count;
    reg p_clk;
    reg p_reset;

    shift_counter ctr(.count(p_count), .clk(p_clk), .reset(p_reset));

    initial begin
        p_clk = 1'b0;
        forever #5 p_clk = ~p_clk;
    end

    initial begin
        p_reset = 1'b1;
        #15 p_reset = 1'b0;
        #200 p_reset = 1'b1;
        #15 p_reset = 1'b0;
        #200 $finish;
    end

    initial begin
        $monitor($time, "reset=%b, count=%b",
                        p_reset, p_count);
        $dumpfile("tb_shift_counter.vcd");
        $dumpvars(0, tb_shift_counter);
    end
endmodule

finalProject/2_13/tb_shift_counter.vcd
$date
	Sat Nov 23 10:53:03 2019
$end
$version
	Icarus Verilog
$end
$timescale
	1ns
$end
$scope module tb_shift_counter $end
$var wire 8 ! p_count [7:0] $end
$var reg 1 " p_clk $end
$var reg 1 # p_reset $end
$scope module ctr $end
$var wire 1 " clk $end
$var wire 1 # reset $end
$var reg 8 $ count [7:0] $end
$var reg 1 % dir $end
$var reg 10 & internal [9:0] $end
$upscope $end
$upscope $end
$enddefinitions $end
#0
$dumpvars
bx &
x%
bx $
1#
0"
bx !
$end
#50
1%
b1 &
1"
#100
0"
#150
b1 !
b1 $
b10 &
1"
0#
#200
0"
#250
b100 &
1"
#300
0"
#350
b1000 &
1"
#400
0"
#450
b10 !
b10 $
b10000 &
1"
#500
0"
#550
b100 !
b100 $
b100000 &
1"
#600
0"
#650
b1000 !
b1000 $
b1000000 &
1"
#700
0"
#750
b10000 !
b10000 $
b10000000 &
1"
#800
0"
#850
b100000 !
b100000 $
b100000000 &
1"
#900
0"
#950
b1000000 !
b1000000 $
b1000000000 &
1"
#1000
0"
#1050
b10000000 !
b10000000 $
0%
1"
#1100
0"
#1150
b100000000 &
1"
#1200
0"
#1250
b1000000 !
b1000000 $
b10000000 &
1"
#1300
0"
#1350
b100000 !
b100000 $
b1000000 &
1"
#1400
0"
#1450
b10000 !
b10000 $
b100000 &
1"
#1500
0"
#1550
b1000 !
b1000 $
b10000 &
1"
#1600
0"
#1650
b100 !
b100 $
b1000 &
1"
#1700
0"
#1750
b10 !
b10 $
b100 &
1"
#1800
0"
#1850
b1 !
b1 $
1%
1"
#1900
0"
#1950
b1000 &
1"
#2000
0"
#2050
b10 !
b10 $
b10000 &
1"
#2100
0"
#2150
b1 &
1"
1#
#2200
0"
#2250
1"
#2300
0"
0#
#2350
b1 !
b1 $
b10 &
1"
#2400
0"
#2450
b100 &
1"
#2500
0"
#2550
b1000 &
1"
#2600
0"
#2650
b10 !
b10 $
b10000 &
1"
#2700
0"
#2750
b100 !
b100 $
b100000 &
1"
#2800
0"
#2850
b1000 !
b1000 $
b1000000 &
1"
#2900
0"
#2950
b10000 !
b10000 $
b10000000 &
1"
#3000
0"
#3050
b100000 !
b100000 $
b100000000 &
1"
#3100
0"
#3150
b1000000 !
b1000000 $
b1000000000 &
1"
#3200
0"
#3250
b10000000 !
b10000000 $
0%
1"
#3300
0"
#3350
b100000000 &
1"
#3400
0"
#3450
b1000000 !
b1000000 $
b10000000 &
1"
#3500
0"
#3550
b100000 !
b100000 $
b1000000 &
1"
#3600
0"
#3650
b10000 !
b10000 $
b100000 &
1"
#3700
0"
#3750
b1000 !
b1000 $
b10000 &
1"
#3800
0"
#3850
b100 !
b100 $
b1000 &
1"
#3900
0"
#3950
b10 !
b10 $
b100 &
1"
#4000
0"
#4050
b1 !
b1 $
1%
1"
#4100
0"
#4150
b1000 &
1"
#4200
0"
#4250
b10 !
b10 $
b10000 &
1"
