dailyExercise/seq_detect/seq_detect_1.v
module seq_detect(output reg flag, input clk, reset, seq);
    parameter   IDLE = 5'b0_0001, A = 5'b0_0010, B = 5'b0_0010,
                   C = 5'b0_1000, D = 5'b1_0000;
    reg [4:0] state;
    always @(posedge clk, negedge reset) begin
        if(!reset)  begin   flag <= 1'b0;   state <= IDLE;  end
        else begin
            case (state)
                IDLE:   if(seq) begin   flag <= 1'b0;   state <= A; end
                        else    begin   flag <= 1'b0;   state <= IDLE;   end
                   A:   if(seq) begin   flag <= 1'b0;   state <= A; end
                        else    begin   flag <= 1'b0;   state <= B;  end
                   B:   if(seq) begin   flag <= 1'b0;   state <= A; end
                        else    begin   flag <= 1'b0;   state <= C;   end
                   C:   if(seq) begin   flag <= 1'b0;   state <= D; end
                        else    begin   flag <= 1'b0;   state <= IDLE;   end
                   D:   if(seq) begin   flag <= 1'b0;   state <= A; end
                        else    begin   flag <= 1'b1;   state <= B;   end
                default:        begin   flag <= 1'b0;   state <= IDLE;  end
            endcase
        end
    end
endmodule

dailyExercise/seq_detect/top.v
`include "seq_detect_1.v"
`timescale 1ns / 100ps
module top;
    wire p_flag;
    reg p_clk, p_rst, p_s;

    initial begin 
        p_rst = 1'b0; 
        #25 p_rst = 1'b1; 
    end

    initial begin 
        p_clk = 0;
        forever #5 p_clk = ~p_clk; 
    end

    parameter SIZE = 32;
    reg [SIZE-1:0] data = 32'b0110_0100_1000_0100_1010_1011_0001_0100;

    initial begin: SERIES
        integer i;
        #1 p_s = 0;
        #30;
        for(i = 0;i < SIZE; i = i + 1) begin
            p_s = data[SIZE-1];
            data = data << 1;
            #20;
        end
        #30 $finish;
    end

    seq_detect u(.flag(p_flag), .clk(p_clk), .reset(p_rst), .seq(p_s));

    initial begin
        $monitor($time, " reset=%b, flag=%b, seq=%b, state=%b",
                        p_rst, p_flag, u.seq, u.state);
        $dumpfile("top.vcd");
        $dumpvars(0, top);
    end
endmodule

dailyExercise/seq_detect/top.vcd
$date
	Sat Nov 23 16:22:44 2019
$end
$version
	Icarus Verilog
$end
$timescale
	100ps
$end
$scope module top $end
$var wire 1 ! p_flag $end
$var reg 32 " data [31:0] $end
$var reg 1 # p_clk $end
$var reg 1 $ p_rst $end
$var reg 1 % p_s $end
$scope module u $end
$var wire 1 # clk $end
$var wire 1 $ reset $end
$var wire 1 % seq $end
$var reg 1 ! flag $end
$var reg 5 & state [4:0] $end
$upscope $end
$scope begin SERIES $end
$var integer 32 ' i [31:0] $end
$upscope $end
$upscope $end
$enddefinitions $end
#0
$dumpvars
bx '
b1 &
x%
0$
0#
b1100100100001001010101100010100 "
0!
$end
#10
0%
#50
1#
#100
0#
#150
1#
#200
0#
#250
1#
1$
#300
0#
#310
b11001001000010010101011000101000 "
b0 '
#350
1#
#400
0#
#450
1#
#500
0#
#510
b10010010000100101010110001010000 "
1%
b1 '
#550
b10 &
1#
#600
0#
#650
1#
#700
0#
#710
b100100001001010101100010100000 "
b10 '
#750
1#
#800
0#
#850
1#
#900
0#
#910
b1001000010010101011000101000000 "
0%
b11 '
#950
1#
#1000
0#
#1050
1#
#1100
0#
#1110
b10010000100101010110001010000000 "
b100 '
#1150
1#
#1200
0#
#1250
1#
#1300
0#
#1310
b100001001010101100010100000000 "
1%
b101 '
#1350
1#
#1400
0#
#1450
1#
#1500
0#
#1510
b1000010010101011000101000000000 "
0%
b110 '
#1550
1#
#1600
0#
#1650
1#
#1700
0#
#1710
b10000100101010110001010000000000 "
b111 '
#1750
1#
#1800
0#
#1850
1#
#1900
0#
#1910
b1001010101100010100000000000 "
1%
b1000 '
#1950
1#
#2000
0#
#2050
1#
#2100
0#
#2110
b10010101011000101000000000000 "
0%
b1001 '
#2150
1#
#2200
0#
#2250
1#
#2300
0#
#2310
b100101010110001010000000000000 "
b1010 '
#2350
1#
#2400
0#
#2450
1#
#2500
0#
#2510
b1001010101100010100000000000000 "
b1011 '
#2550
1#
#2600
0#
#2650
1#
#2700
0#
#2710
b10010101011000101000000000000000 "
b1100 '
#2750
1#
#2800
0#
#2850
1#
#2900
0#
#2910
b101010110001010000000000000000 "
1%
b1101 '
#2950
1#
#3000
0#
#3050
1#
#3100
0#
#3110
b1010101100010100000000000000000 "
0%
b1110 '
#3150
1#
#3200
0#
#3250
1#
#3300
0#
#3310
b10101011000101000000000000000000 "
b1111 '
#3350
1#
#3400
0#
#3450
1#
#3500
0#
#3510
b1010110001010000000000000000000 "
1%
b10000 '
#3550
1#
#3600
0#
#3650
1#
#3700
0#
#3710
b10101100010100000000000000000000 "
0%
b10001 '
#3750
1#
#3800
0#
#3850
1#
#3900
0#
#3910
b1011000101000000000000000000000 "
1%
b10010 '
#3950
1#
#4000
0#
#4050
1#
#4100
0#
#4110
b10110001010000000000000000000000 "
0%
b10011 '
#4150
1#
#4200
0#
#4250
1#
#4300
0#
#4310
b1100010100000000000000000000000 "
1%
b10100 '
#4350
1#
#4400
0#
#4450
1#
#4500
0#
#4510
b11000101000000000000000000000000 "
0%
b10101 '
#4550
1#
#4600
0#
#4650
1#
#4700
0#
#4710
b10001010000000000000000000000000 "
1%
b10110 '
#4750
1#
#4800
0#
#4850
1#
#4900
0#
#4910
b10100000000000000000000000000 "
b10111 '
#4950
1#
#5000
0#
#5050
1#
#5100
0#
#5110
b101000000000000000000000000000 "
0%
b11000 '
#5150
1#
#5200
0#
#5250
1#
#5300
0#
#5310
b1010000000000000000000000000000 "
b11001 '
#5350
1#
#5400
0#
#5450
1#
#5500
0#
#5510
b10100000000000000000000000000000 "
b11010 '
#5550
1#
#5600
0#
#5650
1#
#5700
0#
#5710
b1000000000000000000000000000000 "
1%
b11011 '
#5750
1#
#5800
0#
#5850
1#
#5900
0#
#5910
b10000000000000000000000000000000 "
0%
b11100 '
#5950
1#
#6000
0#
#6050
1#
#6100
0#
#6110
b0 "
1%
b11101 '
#6150
1#
#6200
0#
#6250
1#
#6300
0#
#6310
0%
b11110 '
#6350
1#
#6400
0#
#6450
1#
#6500
0#
#6510
b11111 '
#6550
1#
#6600
0#
#6650
1#
#6700
0#
#6710
b100000 '
