dailyExercise/chanel_sw/chanel_sw_8b.v
module chanel_sw_8b(output [7:0] y_out, input [7:0] d_in, input ctrl);
    assign y_out = (ctrl == 1'b1) ?  d_in : 8'h00;
endmodule

dailyExercise/chanel_sw/top.v
`include "chanel_sw_8b.v"
`timescale 1ns / 100ps
// 八位数据通道控制器
module top;
    reg [7:0] in;
    wire [7:0] out;
    reg ctr;

    chanel_sw_8b sw(.y_out(out), .d_in(in), .ctrl(ctr));
    
    initial
    begin 
        ctr = 1'b0;
        forever #7 ctr = ~ctr;
    end

    initial
    begin
        in = {$random} % 256;
        forever #5 in = {$random} % 256;;
    end

    initial 
        $monitor($time, "ctr = %b, in is %b, out = %b", 
                        ctr, in, out);

    initial
        #50 $finish;

    initial
    begin
        $dumpfile("top.vcd");
        $dumpvars(0, top);
    end
endmodule

dailyExercise/chanel_sw/top.vcd
$date
	Mon Nov 18 17:22:08 2019
$end
$version
	Icarus Verilog
$end
$timescale
	100ps
$end
$scope module top $end
$var wire 8 ! out [7:0] $end
$var reg 1 " ctr $end
$var reg 8 # in [7:0] $end
$scope module sw $end
$var wire 1 " ctrl $end
$var wire 8 $ d_in [7:0] $end
$var wire 8 % y_out [7:0] $end
$upscope $end
$upscope $end
$enddefinitions $end
#0
$dumpvars
b0 %
b100100 $
b100100 #
0"
b0 !
$end
#50
b10000001 #
b10000001 $
#70
b10000001 !
b10000001 %
1"
#100
b1001 !
b1001 %
b1001 #
b1001 $
#140
b0 !
b0 %
0"
#150
b1100011 #
b1100011 $
#200
b1101 #
b1101 $
#210
b1101 !
b1101 %
1"
#250
b10001101 !
b10001101 %
b10001101 #
b10001101 $
#280
b0 !
b0 %
0"
#300
b1100101 #
b1100101 $
#350
b10010 !
b10010 %
b10010 #
b10010 $
1"
#400
b1 !
b1 %
b1 #
b1 $
#420
b0 !
b0 %
0"
#450
b1101 #
b1101 $
#490
b1101 !
b1101 %
1"
