finalProject/2_16/mealy.v
module mealy(output reg flag, input din, clk, rst);
    reg [7:0] p_state, n_state;
    parameter   IDLE = 8'b0000_0001,
                A = 8'b0000_0010,
                B = 8'b0000_0100,
                C = 8'b0000_1000,
                D = 8'b0001_0000,
                E = 8'b0010_0000,
                F = 8'b0100_0000,
                G = 8'b1000_0000;

    always @(posedge clk, posedge rst) begin
        if( rst ) p_state <= IDLE;
        else p_state <= n_state;
        flag <= ((p_state == G ) && (din == 1'b1)) ? 1'b1 : 1'b0 ; 

    end     

    always @(*) begin
        case (p_state)
            IDLE:n_state <= (din) ? IDLE  : A ; 
            A:   n_state <= (din) ? B     : A ; 
            B:   n_state <= (din) ? IDLE  : C ; 
            C:   n_state <= (din) ? D     : A ; 
            D:   n_state <= (din) ? IDLE  : E ; 
            E:   n_state <= (din) ? F     : A ; 
            F:   n_state <= (din) ? IDLE  : G ; 
            G:   n_state <= (din) ? F     : A ; 
            default:n_state <= IDLE;
        endcase
    end  

endmodule

finalProject/2_16/moore.v
module moore(output reg flag, input din, clk, rst);
    reg [8:0] state;
    parameter   IDLE = 9'b1_0000_0000,
                A = 9'b0_0000_0001, 
                B = 9'b0_0000_0010,
                C = 9'b0_0000_0100, 
                D = 9'b0_0000_1000,
                E = 9'b0_0001_0000, 
                F = 9'b0_0010_0000,
                G = 9'b0_0100_0000, 
                H = 9'b0_1000_0000;
    
    always @(posedge clk, posedge rst) begin
        if( rst ) begin state <= IDLE; flag <= 1'b0;    end
        else begin
            flag <= (state == H) ? 1'b1 : 1'b0;
            case (state)
                IDLE:state <= (din) ? IDLE  : A ; 
                A:   state <= (din) ? B     : A ; 
                B:   state <= (din) ? IDLE  : C ; 
                C:   state <= (din) ? D     : A ; 
                D:   state <= (din) ? IDLE  : E ; 
                E:   state <= (din) ? F     : A ; 
                F:   state <= (din) ? IDLE  : G ; 
                G:   state <= (din) ? H     : A ; 
                H:   state <= (din) ? IDLE  : G ; 
                default:    state <= IDLE;
            endcase
        end
    end
endmodule

finalProject/2_16/top.v
`include "moore.v"
`include "mealy.v"
`timescale 10ns/ 1ns
module top();
    wire p_flag_moore, p_flag_mealy;
    reg p_din, p_clk, p_rst;

    reg [35:0] data = 36'b1010_1010_0010_1010_1001_1010_0010_1010_1000;

    moore mo(.flag(p_flag_moore), .din(p_din), .clk(p_clk), .rst(p_rst));
    mealy me(.flag(p_flag_mealy), .din(p_din), .clk(p_clk), .rst(p_rst));

    initial begin
        p_clk = 1'b0;
        forever #5 p_clk = ~p_clk;
    end

    integer k;
    initial 
    begin
        p_rst = 1'b1;
        p_din = 1'bx;
        #12 p_rst = 1'b0;
        for(k = 0; k < 36; k = k + 1)
        begin
            p_din = data[0];
            data = data >> 1;
            #10;
        end
        #20 $finish;
    end

    initial begin
        $monitor($time, " rst = %b, din = %b, flag_moore = %b, flag_mealy = %b",
                        p_rst, p_din, p_flag_moore, p_flag_mealy);
        $dumpfile("top.vcd");
        $dumpvars(0, top);
    end
endmodule

finalProject/2_16/top.vcd
$date
	Sat Nov 23 18:02:23 2019
$end
$version
	Icarus Verilog
$end
$timescale
	1ns
$end
$scope module top $end
$var wire 1 ! p_flag_moore $end
$var wire 1 " p_flag_mealy $end
$var reg 36 # data [35:0] $end
$var reg 1 $ p_clk $end
$var reg 1 % p_din $end
$var reg 1 & p_rst $end
$var integer 32 ' k [31:0] $end
$scope module me $end
$var wire 1 $ clk $end
$var wire 1 % din $end
$var wire 1 & rst $end
$var reg 1 " flag $end
$var reg 8 ( n_state [7:0] $end
$var reg 8 ) p_state [7:0] $end
$upscope $end
$scope module mo $end
$var wire 1 $ clk $end
$var wire 1 % din $end
$var wire 1 & rst $end
$var reg 1 ! flag $end
$var reg 9 * state [8:0] $end
$upscope $end
$upscope $end
$enddefinitions $end
#0
$dumpvars
b100000000 *
b1 )
b0xx (
bx '
1&
x%
0$
b101010100010101010011010001010101000 #
x"
0!
$end
#50
0"
1$
#100
0$
#120
b10 (
b10101010001010101001101000101010100 #
0%
b0 '
0&
#150
b1 *
b10 )
1$
#200
0$
#220
b1010101000101010100110100010101010 #
b1 '
#250
1$
#300
0$
#320
b101010100010101010011010001010101 #
b10 '
#350
1$
#400
0$
#420
b100 (
b10101010001010101001101000101010 #
1%
b11 '
#450
b1 (
b100 )
b10 *
1$
#500
0$
#520
b1000 (
b1010101000101010100110100010101 #
0%
b100 '
#550
b10 (
b100 *
b1000 )
1$
#600
0$
#620
b10000 (
b101010100010101010011010001010 #
1%
b101 '
#650
b1 (
b10000 )
b1000 *
1$
#700
0$
#720
b100000 (
b10101010001010101001101000101 #
0%
b110 '
#750
b10 (
b10000 *
b100000 )
1$
#800
0$
#820
b1000000 (
b1010101000101010100110100010 #
1%
b111 '
#850
b1 (
b1000000 )
b100000 *
1$
#900
0$
#920
b10000000 (
b101010100010101010011010001 #
0%
b1000 '
#950
b10 (
b1000000 *
b10000000 )
1$
#1000
0$
#1020
b1000000 (
b10101010001010101001101000 #
1%
b1001 '
#1050
b1 (
1"
b1000000 )
b10000000 *
1$
#1100
0$
#1120
b10000000 (
b1010101000101010100110100 #
0%
b1010 '
#1150
b10 (
b1000000 *
1!
0"
b10000000 )
1$
#1200
0$
#1220
b101010100010101010011010 #
b1011 '
#1250
b10 )
b1 *
0!
1$
#1300
0$
#1320
b10101010001010101001101 #
b1100 '
#1350
1$
#1400
0$
#1420
b100 (
b1010101000101010100110 #
1%
b1101 '
#1450
b1 (
b100 )
b10 *
1$
#1500
0$
#1520
b1000 (
b101010100010101010011 #
0%
b1110 '
#1550
b10 (
b100 *
b1000 )
1$
#1600
0$
#1620
b10000 (
b10101010001010101001 #
1%
b1111 '
#1650
b1 (
b10000 )
b1000 *
1$
#1700
0$
#1720
b1010101000101010100 #
b10000 '
#1750
b100000000 *
b1 )
1$
#1800
0$
#1820
b10 (
b101010100010101010 #
0%
b10001 '
#1850
b10 )
b1 *
1$
#1900
0$
#1920
b10101010001010101 #
b10010 '
#1950
1$
#2000
0$
#2020
b100 (
b1010101000101010 #
1%
b10011 '
#2050
b1 (
b100 )
b10 *
1$
#2100
0$
#2120
b1000 (
b101010100010101 #
0%
b10100 '
#2150
b10 (
b100 *
b1000 )
1$
#2200
0$
#2220
b10000 (
b10101010001010 #
1%
b10101 '
#2250
b1 (
b10000 )
b1000 *
1$
#2300
0$
#2320
b100000 (
b1010101000101 #
0%
b10110 '
#2350
b10 (
b10000 *
b100000 )
1$
#2400
0$
#2420
b1000000 (
b101010100010 #
1%
b10111 '
#2450
b1 (
b1000000 )
b100000 *
1$
#2500
0$
#2520
b10000000 (
b10101010001 #
0%
b11000 '
#2550
b10 (
b1000000 *
b10000000 )
1$
#2600
0$
#2620
b1000000 (
b1010101000 #
1%
b11001 '
#2650
b1 (
1"
b1000000 )
b10000000 *
1$
#2700
0$
#2720
b10000000 (
b101010100 #
0%
b11010 '
#2750
b10 (
b1000000 *
1!
0"
b10000000 )
1$
#2800
0$
#2820
b10101010 #
b11011 '
#2850
b10 )
b1 *
0!
1$
#2900
0$
#2920
b1010101 #
b11100 '
#2950
1$
#3000
0$
#3020
b100 (
b101010 #
1%
b11101 '
#3050
b1 (
b100 )
b10 *
1$
#3100
0$
#3120
b1000 (
b10101 #
0%
b11110 '
#3150
b10 (
b100 *
b1000 )
1$
#3200
0$
#3220
b10000 (
b1010 #
1%
b11111 '
#3250
b1 (
b10000 )
b1000 *
1$
#3300
0$
#3320
b100000 (
b101 #
0%
b100000 '
#3350
b10 (
b10000 *
b100000 )
1$
#3400
0$
#3420
b1000000 (
b10 #
1%
b100001 '
#3450
b1 (
b1000000 )
b100000 *
1$
#3500
0$
#3520
b10000000 (
b1 #
0%
b100010 '
#3550
b10 (
b1000000 *
b10000000 )
1$
#3600
0$
#3620
b1000000 (
b0 #
1%
b100011 '
#3650
b1 (
1"
b1000000 )
b10000000 *
1$
#3700
0$
#3720
b100100 '
#3750
b100000000 *
1!
0"
b1 )
1$
#3800
0$
#3850
0!
1$
