finalProject/2_14/sram.v
module sram(output  [7:0] dout,
            input   [7:0] din,
            input   [7:0] addr,
            input   wr,
            input   rd,
            input   cs
            );
    reg [7:0] mem [255:0];
    reg [7:0] data;

    assign dout = (cs && ~wr && rd )? data : 8'bz;
    always @(*) begin
        if(cs)  // chip select
            case ({wr,rd})
                2'b10:  mem[addr] <= din;   // write
                2'b01:  data <= mem[addr];  // read
                default:;
            endcase
    end
endmodule

finalProject/2_14/tb_sram.v
`include "sram.v"
`timescale 10ns / 1ns 
module tb_sram();
    reg [7:0] p_din;
    reg [7:0] p_addr;
    reg p_wr,p_rd,p_cs;
    wire [7:0] p_dout;

    sram ram(.din(p_din), .addr(p_addr), .wr(p_wr), .rd(p_rd), .cs(p_cs), .dout(p_dout));

    integer k;
    initial begin
        p_cs = 1'b1;
        p_wr = 1'b1;
        p_rd = 1'b0;
        for(k = 0; k < 256;k = k + 1) begin:WRITE
            #10;
            p_addr = k;
            p_din = {$random} % 256;
        end
        #20 p_cs = 1'b0;
        #20 p_cs = 1'b1;
        p_wr = 1'b0;
        p_rd = 1'b1;
        p_din = 8'bz;
        for(k = 0; k < 8; k = k + 1 )begin:READ
            #10;
            p_addr = {$random} % 256;
        end
        #20 $finish;
    end

    initial begin
        $monitor($time, " en=%b%b%b, addr=%d, din=%d, dout=%d",
                        p_cs, p_wr, p_rd, p_addr, p_din, p_dout);
        $dumpfile("tb_sram.vcd");
        $dumpvars(0, tb_sram);
    end
endmodule

finalProject/2_14/tb_sram.vcd
$date
	Sat Nov 23 11:18:43 2019
$end
$version
	Icarus Verilog
$end
$timescale
	1ns
$end
$scope module tb_sram $end
$var wire 8 ! p_dout [7:0] $end
$var reg 8 " p_addr [7:0] $end
$var reg 1 # p_cs $end
$var reg 8 $ p_din [7:0] $end
$var reg 1 % p_rd $end
$var reg 1 & p_wr $end
$var integer 32 ' k [31:0] $end
$scope module ram $end
$var wire 8 ( addr [7:0] $end
$var wire 1 # cs $end
$var wire 8 ) din [7:0] $end
$var wire 1 % rd $end
$var wire 1 & wr $end
$var wire 8 * dout [7:0] $end
$var reg 8 + data [7:0] $end
$upscope $end
$scope begin READ $end
$upscope $end
$scope begin WRITE $end
$upscope $end
$upscope $end
$enddefinitions $end
#0
$dumpvars
bx +
bz *
bx )
bx (
b0 '
1&
0%
bx $
1#
bx "
bz !
$end
#100
b1 '
b100100 $
b100100 )
b0 "
b0 (
#200
b10 '
b10000001 $
b10000001 )
b1 "
b1 (
#300
b11 '
b1001 $
b1001 )
b10 "
b10 (
#400
b100 '
b1100011 $
b1100011 )
b11 "
b11 (
#500
b101 '
b1101 $
b1101 )
b100 "
b100 (
#600
b110 '
b10001101 $
b10001101 )
b101 "
b101 (
#700
b111 '
b1100101 $
b1100101 )
b110 "
b110 (
#800
b1000 '
b10010 $
b10010 )
b111 "
b111 (
#900
b1001 '
b1 $
b1 )
b1000 "
b1000 (
#1000
b1010 '
b1101 $
b1101 )
b1001 "
b1001 (
#1100
b1011 '
b1110110 $
b1110110 )
b1010 "
b1010 (
#1200
b1100 '
b111101 $
b111101 )
b1011 "
b1011 (
#1300
b1101 '
b11101101 $
b11101101 )
b1100 "
b1100 (
#1400
b1110 '
b10001100 $
b10001100 )
b1101 "
b1101 (
#1500
b1111 '
b11111001 $
b11111001 )
b1110 "
b1110 (
#1600
b10000 '
b11000110 $
b11000110 )
b1111 "
b1111 (
#1700
b10001 '
b11000101 $
b11000101 )
b10000 "
b10000 (
#1800
b10010 '
b10101010 $
b10101010 )
b10001 "
b10001 (
#1900
b10011 '
b11100101 $
b11100101 )
b10010 "
b10010 (
#2000
b10100 '
b1110111 $
b1110111 )
b10011 "
b10011 (
#2100
b10101 '
b10010 $
b10010 )
b10100 "
b10100 (
#2200
b10110 '
b10001111 $
b10001111 )
b10101 "
b10101 (
#2300
b10111 '
b11110010 $
b11110010 )
b10110 "
b10110 (
#2400
b11000 '
b11001110 $
b11001110 )
b10111 "
b10111 (
#2500
b11001 '
b11101000 $
b11101000 )
b11000 "
b11000 (
#2600
b11010 '
b11000101 $
b11000101 )
b11001 "
b11001 (
#2700
b11011 '
b1011100 $
b1011100 )
b11010 "
b11010 (
#2800
b11100 '
b10111101 $
b10111101 )
b11011 "
b11011 (
#2900
b11101 '
b101101 $
b101101 )
b11100 "
b11100 (
#3000
b11110 '
b1100101 $
b1100101 )
b11101 "
b11101 (
#3100
b11111 '
b1100011 $
b1100011 )
b11110 "
b11110 (
#3200
b100000 '
b1010 $
b1010 )
b11111 "
b11111 (
#3300
b100001 '
b10000000 $
b10000000 )
b100000 "
b100000 (
#3400
b100010 '
b100000 $
b100000 )
b100001 "
b100001 (
#3500
b100011 '
b10101010 $
b10101010 )
b100010 "
b100010 (
#3600
b100100 '
b10011101 $
b10011101 )
b100011 "
b100011 (
#3700
b100101 '
b10010110 $
b10010110 )
b100100 "
b100100 (
#3800
b100110 '
b10011 $
b10011 )
b100101 "
b100101 (
#3900
b100111 '
b1101 $
b1101 )
b100110 "
b100110 (
#4000
b101000 '
b1010011 $
b1010011 )
b100111 "
b100111 (
#4100
b101001 '
b1101011 $
b1101011 )
b101000 "
b101000 (
#4200
b101010 '
b11010101 $
b11010101 )
b101001 "
b101001 (
#4300
b101011 '
b10 $
b10 )
b101010 "
b101010 (
#4400
b101100 '
b10101110 $
b10101110 )
b101011 "
b101011 (
#4500
b101101 '
b11101 $
b11101 )
b101100 "
b101100 (
#4600
b101110 '
b11001111 $
b11001111 )
b101101 "
b101101 (
#4700
b101111 '
b100011 $
b100011 )
b101110 "
b101110 (
#4800
b110000 '
b1010 $
b1010 )
b101111 "
b101111 (
#4900
b110001 '
b11001010 $
b11001010 )
b110000 "
b110000 (
#5000
b110010 '
b111100 $
b111100 )
b110001 "
b110001 (
#5100
b110011 '
b11110010 $
b11110010 )
b110010 "
b110010 (
#5200
b110100 '
b10001010 $
b10001010 )
b110011 "
b110011 (
#5300
b110101 '
b1000001 $
b1000001 )
b110100 "
b110100 (
#5400
b110110 '
b11011000 $
b11011000 )
b110101 "
b110101 (
#5500
b110111 '
b1111000 $
b1111000 )
b110110 "
b110110 (
#5600
b111000 '
b10001001 $
b10001001 )
b110111 "
b110111 (
#5700
b111001 '
b11101011 $
b11101011 )
b111000 "
b111000 (
#5800
b111010 '
b10110110 $
b10110110 )
b111001 "
b111001 (
#5900
b111011 '
b11000110 $
b11000110 )
b111010 "
b111010 (
#6000
b111100 '
b10101110 $
b10101110 )
b111011 "
b111011 (
#6100
b111101 '
b10111100 $
b10111100 )
b111100 "
b111100 (
#6200
b111110 '
b101010 $
b101010 )
b111101 "
b111101 (
#6300
b111111 '
b1011 $
b1011 )
b111110 "
b111110 (
#6400
b1000000 '
b1110001 $
b1110001 )
b111111 "
b111111 (
#6500
b1000001 '
b10000101 $
b10000101 )
b1000000 "
b1000000 (
#6600
b1000010 '
b1001111 $
b1001111 )
b1000001 "
b1000001 (
#6700
b1000011 '
b111011 $
b111011 )
b1000010 "
b1000010 (
#6800
b1000100 '
b111010 $
b111010 )
b1000011 "
b1000011 (
#6900
b1000101 '
b1111110 $
b1111110 )
b1000100 "
b1000100 (
#7000
b1000110 '
b10101 $
b10101 )
b1000101 "
b1000101 (
#7100
b1000111 '
b11110001 $
b11110001 )
b1000110 "
b1000110 (
#7200
b1001000 '
b11011001 $
b11011001 )
b1000111 "
b1000111 (
#7300
b1001001 '
b1100010 $
b1100010 )
b1001000 "
b1001000 (
#7400
b1001010 '
b1001100 $
b1001100 )
b1001001 "
b1001001 (
#7500
b1001011 '
b10011111 $
b10011111 )
b1001010 "
b1001010 (
#7600
b1001100 '
b10001111 $
b10001111 )
b1001011 "
b1001011 (
#7700
b1001101 '
b11111000 $
b11111000 )
b1001100 "
b1001100 (
#7800
b1001110 '
b10110111 $
b10110111 )
b1001101 "
b1001101 (
#7900
b1001111 '
b10011111 $
b10011111 )
b1001110 "
b1001110 (
#8000
b1010000 '
b1011100 $
b1011100 )
b1001111 "
b1001111 (
#8100
b1010001 '
b1011011 $
b1011011 )
b1010000 "
b1010000 (
#8200
b1010010 '
b10001001 $
b10001001 )
b1010001 "
b1010001 (
#8300
b1010011 '
b1001001 $
b1001001 )
b1010010 "
b1010010 (
#8400
b1010100 '
b11010000 $
b11010000 )
b1010011 "
b1010011 (
#8500
b1010101 '
b11010111 $
b11010111 )
b1010100 "
b1010100 (
#8600
b1010110 '
b1010001 $
b1010001 )
b1010101 "
b1010101 (
#8700
b1010111 '
b10010110 $
b10010110 )
b1010110 "
b1010110 (
#8800
b1011000 '
b1100 $
b1100 )
b1010111 "
b1010111 (
#8900
b1011001 '
b11000010 $
b11000010 )
b1011000 "
b1011000 (
#9000
b1011010 '
b11001000 $
b11001000 )
b1011001 "
b1011001 (
#9100
b1011011 '
b1110111 $
b1110111 )
b1011010 "
b1011010 (
#9200
b1011100 '
b111101 $
b111101 )
b1011011 "
b1011011 (
#9300
b1011101 '
b10010 $
b10010 )
b1011100 "
b1011100 (
#9400
b1011110 '
b1111110 $
b1111110 )
b1011101 "
b1011101 (
#9500
b1011111 '
b1101101 $
b1101101 )
b1011110 "
b1011110 (
#9600
b1100000 '
b111001 $
b111001 )
b1011111 "
b1011111 (
#9700
b1100001 '
b11111 $
b11111 )
b1100000 "
b1100000 (
#9800
b1100010 '
b11010011 $
b11010011 )
b1100001 "
b1100001 (
#9900
b1100011 '
b10000101 $
b10000101 )
b1100010 "
b1100010 (
#10000
b1100100 '
b1111000 $
b1111000 )
b1100011 "
b1100011 (
#10100
b1100101 '
b1011011 $
b1011011 )
b1100100 "
b1100100 (
#10200
b1100110 '
b1001001 $
b1001001 )
b1100101 "
b1100101 (
#10300
b1100111 '
b111111 $
b111111 )
b1100110 "
b1100110 (
#10400
b1101000 '
b101010 $
b101010 )
b1100111 "
b1100111 (
#10500
b1101001 '
b1011000 $
b1011000 )
b1101000 "
b1101000 (
#10600
b1101010 '
b10000110 $
b10000110 )
b1101001 "
b1101001 (
#10700
b1101011 '
b10001110 $
b10001110 )
b1101010 "
b1101010 (
#10800
b1101100 '
b10011100 $
b10011100 )
b1101011 "
b1101011 (
#10900
b1101101 '
b11111010 $
b11111010 )
b1101100 "
b1101100 (
#11000
b1101110 '
b100110 $
b100110 )
b1101101 "
b1101101 (
#11100
b1101111 '
b1110011 $
b1110011 )
b1101110 "
b1101110 (
#11200
b1110000 '
b10100011 $
b10100011 )
b1101111 "
b1101111 (
#11300
b1110001 '
b101111 $
b101111 )
b1110000 "
b1110000 (
#11400
b1110010 '
b10110011 $
b10110011 )
b1110001 "
b1110001 (
#11500
b1110011 '
b1011111 $
b1011111 )
b1110010 "
b1110010 (
#11600
b1110100 '
b1000100 $
b1000100 )
b1110011 "
b1110011 (
#11700
b1110101 '
b11110111 $
b11110111 )
b1110100 "
b1110100 (
#11800
b1110110 '
b11001011 $
b11001011 )
b1110101 "
b1110101 (
#11900
b1110111 '
b11100110 $
b11100110 )
b1110110 "
b1110110 (
#12000
b1111000 '
b1011010 $
b1011010 )
b1110111 "
b1110111 (
#12100
b1111001 '
b101001 $
b101001 )
b1111000 "
b1111000 (
#12200
b1111010 '
b11101101 $
b11101101 )
b1111001 "
b1111001 (
#12300
b1111011 '
b11011010 $
b11011010 )
b1111010 "
b1111010 (
#12400
b1111100 '
b1100101 $
b1100101 )
b1111011 "
b1111011 (
#12500
b1111101 '
b10110101 $
b10110101 )
b1111100 "
b1111100 (
#12600
b1111110 '
b11011111 $
b11011111 )
b1111101 "
b1111101 (
#12700
b1111111 '
b1111001 $
b1111001 )
b1111110 "
b1111110 (
#12800
b10000000 '
b1000100 $
b1000100 )
b1111111 "
b1111111 (
#12900
b10000001 '
b11010000 $
b11010000 )
b10000000 "
b10000000 (
#13000
b10000010 '
b101010 $
b101010 )
b10000001 "
b10000001 (
#13100
b10000011 '
b10101011 $
b10101011 )
b10000010 "
b10000010 (
#13200
b10000100 '
b1110 $
b1110 )
b10000011 "
b10000011 (
#13300
b10000101 '
b11011100 $
b11011100 )
b10000100 "
b10000100 (
#13400
b10000110 '
b10011010 $
b10011010 )
b10000101 "
b10000101 (
#13500
b10000111 '
b11111101 $
b11111101 )
b10000110 "
b10000110 (
#13600
b10001000 '
b11000011 $
b11000011 )
b10000111 "
b10000111 (
#13700
b10001001 '
b1010110 $
b1010110 )
b10001000 "
b10001000 (
#13800
b10001010 '
b1001110 $
b1001110 )
b10001001 "
b10001001 (
#13900
b10001011 '
b1100111 $
b1100111 )
b10001010 "
b10001010 (
#14000
b10001100 '
b1010 $
b1010 )
b10001011 "
b10001011 (
#14100
b10001101 '
b10110110 $
b10110110 )
b10001100 "
b10001100 (
#14200
b10001110 '
b111000 $
b111000 )
b10001101 "
b10001101 (
#14300
b10001111 '
b1111001 $
b1111001 )
b10001110 "
b10001110 (
#14400
b10010000 '
b10111000 $
b10111000 )
b10001111 "
b10001111 (
#14500
b10010001 '
b10010100 $
b10010100 )
b10010000 "
b10010000 (
#14600
b10010010 '
b10010011 $
b10010011 )
b10010001 "
b10010001 (
#14700
b10010011 '
b100 $
b100 )
b10010010 "
b10010010 (
#14800
b10010100 '
b1011001 $
b1011001 )
b10010011 "
b10010011 (
#14900
b10010101 '
b11011011 $
b11011011 )
b10010100 "
b10010100 (
#15000
b10010110 '
b1001101 $
b1001101 )
b10010101 "
b10010101 (
#15100
b10010111 '
b11011001 $
b11011001 )
b10010110 "
b10010110 (
#15200
b10011000 '
b1101101 $
b1101101 )
b10010111 "
b10010111 (
#15300
b10011001 '
b1110110 $
b1110110 )
b10011000 "
b10011000 (
#15400
b10011010 '
b11001010 $
b11001010 )
b10011001 "
b10011001 (
#15500
b10011011 '
b10110110 $
b10110110 )
b10011010 "
b10011010 (
#15600
b10011100 '
b10010101 $
b10010101 )
b10011011 "
b10011011 (
#15700
b10011101 '
b1000110 $
b1000110 )
b10011100 "
b10011100 (
#15800
b10011110 '
b100 $
b100 )
b10011101 "
b10011101 (
#15900
b10011111 '
b11110111 $
b11110111 )
b10011110 "
b10011110 (
#16000
b10100000 '
b1101001 $
b1101001 )
b10011111 "
b10011111 (
#16100
b10100001 '
b10110100 $
b10110100 )
b10100000 "
b10100000 (
#16200
b10100010 '
b10001000 $
b10001000 )
b10100001 "
b10100001 (
#16300
b10100011 '
b101000 $
b101000 )
b10100010 "
b10100010 (
#16400
b10100100 '
b101101 $
b101101 )
b10100011 "
b10100011 (
#16500
b10100101 '
b11000111 $
b11000111 )
b10100100 "
b10100100 (
#16600
b10100110 '
b101110 $
b101110 )
b10100101 "
b10100101 (
#16700
b10100111 '
b1000 $
b1000 )
b10100110 "
b10100110 (
#16800
b10101000 '
b11100 $
b11100 )
b10100111 "
b10100111 (
#16900
b10101001 '
b11111101 $
b11111101 )
b10101000 "
b10101000 (
#17000
b10101010 '
b101001 $
b101001 )
b10101001 "
b10101001 (
#17100
b10101011 '
b11100 $
b11100 )
b10101010 "
b10101010 (
#17200
b10101100 '
b10000110 $
b10000110 )
b10101011 "
b10101011 (
#17300
b10101101 '
b11011010 $
b11011010 )
b10101100 "
b10101100 (
#17400
b10101110 '
b111101 $
b111101 )
b10101101 "
b10101101 (
#17500
b10101111 '
b1100110 $
b1100110 )
b10101110 "
b10101110 (
#17600
b10110000 '
b1110000 $
b1110000 )
b10101111 "
b10101111 (
#17700
b10110001 '
b1110011 $
b1110011 )
b10110000 "
b10110000 (
#17800
b10110010 '
b10111010 $
b10111010 )
b10110001 "
b10110001 (
#17900
b10110011 '
b1011110 $
b1011110 )
b10110010 "
b10110010 (
#18000
b10110100 '
b11111010 $
b11111010 )
b10110011 "
b10110011 (
#18100
b10110101 '
b11010101 $
b11010101 )
b10110100 "
b10110100 (
#18200
b10110110 '
b11010 $
b11010 )
b10110101 "
b10110101 (
#18300
b10110111 '
b10111001 $
b10111001 )
b10110110 "
b10110110 (
#18400
b10111000 '
b110111 $
b110111 )
b10110111 "
b10110111 (
#18500
b10111001 '
b10010110 $
b10010110 )
b10111000 "
b10111000 (
#18600
b10111010 '
b11000000 $
b11000000 )
b10111001 "
b10111001 (
#18700
b10111011 '
b100110 $
b100110 )
b10111010 "
b10111010 (
#18800
b10111100 '
b10110110 $
b10110110 )
b10111011 "
b10111011 (
#18900
b10111101 '
b1111101 $
b1111101 )
b10111100 "
b10111100 (
#19000
b10111110 '
b11011100 $
b11011100 )
b10111101 "
b10111101 (
#19100
b10111111 '
b10000110 $
b10000110 )
b10111110 "
b10111110 (
#19200
b11000000 '
b1111000 $
b1111000 )
b10111111 "
b10111111 (
#19300
b11000001 '
b1111110 $
b1111110 )
b11000000 "
b11000000 (
#19400
b11000010 '
b11011011 $
b11011011 )
b11000001 "
b11000001 (
#19500
b11000011 '
b11001111 $
b11001111 )
b11000010 "
b11000010 (
#19600
b11000100 '
b1111001 $
b1111001 )
b11000011 "
b11000011 (
#19700
b11000101 '
b11111010 $
b11111010 )
b11000100 "
b11000100 (
#19800
b11000110 '
b1100001 $
b1100001 )
b11000101 "
b11000101 (
#19900
b11000111 '
b10111 $
b10111 )
b11000110 "
b11000110 (
#20000
b11001000 '
b10100001 $
b10100001 )
b11000111 "
b11000111 (
#20100
b11001001 '
b10000110 $
b10000110 )
b11001000 "
b11001000 (
#20200
b11001010 '
b1010000 $
b1010000 )
b11001001 "
b11001001 (
#20300
b11001011 '
b11110101 $
b11110101 )
b11001010 "
b11001010 (
#20400
b11001100 '
b110101 $
b110101 )
b11001011 "
b11001011 (
#20500
b11001101 '
b101001 $
b101001 )
b11001100 "
b11001100 (
#20600
b11001110 '
b11000001 $
b11000001 )
b11001101 "
b11001101 (
#20700
b11001111 '
b11000101 $
b11000101 )
b11001110 "
b11001110 (
#20800
b11010000 '
b10011000 $
b10011000 )
b11001111 "
b11001111 (
#20900
b11010001 '
b1001011 $
b1001011 )
b11010000 "
b11010000 (
#21000
b11010010 '
b1110011 $
b1110011 )
b11010001 "
b11010001 (
#21100
b11010011 '
b11101100 $
b11101100 )
b11010010 "
b11010010 (
#21200
b11010100 '
b10001010 $
b10001010 )
b11010011 "
b11010011 (
#21300
b11010101 '
b1001110 $
b1001110 )
b11010100 "
b11010100 (
#21400
b11010110 '
b10101000 $
b10101000 )
b11010101 "
b11010101 (
#21500
b11010111 '
b10101001 $
b10101001 )
b11010110 "
b11010110 (
#21600
b11011000 '
b10100001 $
b10100001 )
b11010111 "
b11010111 (
#21700
b11011001 '
b1110 $
b1110 )
b11011000 "
b11011000 (
#21800
b11011010 '
b11100110 $
b11100110 )
b11011001 "
b11011001 (
#21900
b11011011 '
b10011111 $
b10011111 )
b11011010 "
b11011010 (
#22000
b11011100 '
b101010 $
b101010 )
b11011011 "
b11011011 (
#22100
b11011101 '
b11011100 "
b11011100 (
#22200
b11011110 '
b10001101 $
b10001101 )
b11011101 "
b11011101 (
#22300
b11011111 '
b10011110 $
b10011110 )
b11011110 "
b11011110 (
#22400
b11100000 '
b111000 $
b111000 )
b11011111 "
b11011111 (
#22500
b11100001 '
b1111001 $
b1111001 )
b11100000 "
b11100000 (
#22600
b11100010 '
b11001000 $
b11001000 )
b11100001 "
b11100001 (
#22700
b11100011 '
b11001010 $
b11001010 )
b11100010 "
b11100010 (
#22800
b11100100 '
b10011 $
b10011 )
b11100011 "
b11100011 (
#22900
b11100101 '
b1101011 $
b1101011 )
b11100100 "
b11100100 (
#23000
b11100110 '
b11000111 $
b11000111 )
b11100101 "
b11100101 (
#23100
b11100111 '
b10110110 $
b10110110 )
b11100110 "
b11100110 (
#23200
b11101000 '
b10111010 $
b10111010 )
b11100111 "
b11100111 (
#23300
b11101001 '
b11000100 $
b11000100 )
b11101000 "
b11101000 (
#23400
b11101010 '
b10111001 $
b10111001 )
b11101001 "
b11101001 (
#23500
b11101011 '
b10010010 $
b10010010 )
b11101010 "
b11101010 (
#23600
b11101100 '
b10110100 $
b10110100 )
b11101011 "
b11101011 (
#23700
b11101101 '
b1111111 $
b1111111 )
b11101100 "
b11101100 (
#23800
b11101110 '
b10000110 $
b10000110 )
b11101101 "
b11101101 (
#23900
b11101111 '
b11111010 $
b11111010 )
b11101110 "
b11101110 (
#24000
b11110000 '
b11110010 $
b11110010 )
b11101111 "
b11101111 (
#24100
b11110001 '
b110010 $
b110010 )
b11110000 "
b11110000 (
#24200
b11110010 '
b10111101 $
b10111101 )
b11110001 "
b11110001 (
#24300
b11110011 '
b10000100 $
b10000100 )
b11110010 "
b11110010 (
#24400
b11110100 '
b11100100 $
b11100100 )
b11110011 "
b11110011 (
#24500
b11110101 '
b11001010 $
b11001010 )
b11110100 "
b11110100 (
#24600
b11110110 '
b10101001 $
b10101001 )
b11110101 "
b11110101 (
#24700
b11110111 '
b10100001 $
b10100001 )
b11110110 "
b11110110 (
#24800
b11111000 '
b10001110 $
b10001110 )
b11110111 "
b11110111 (
#24900
b11111001 '
b11111011 $
b11111011 )
b11111000 "
b11111000 (
#25000
b11111010 '
b1011 $
b1011 )
b11111001 "
b11111001 (
#25100
b11111011 '
b11101111 $
b11101111 )
b11111010 "
b11111010 (
#25200
b11111100 '
b11001001 $
b11001001 )
b11111011 "
b11111011 (
#25300
b11111101 '
b110110 $
b110110 )
b11111100 "
b11111100 (
#25400
b11111110 '
b1110101 $
b1110101 )
b11111101 "
b11111101 (
#25500
b11111111 '
b10001111 $
b10001111 )
b11111110 "
b11111110 (
#25600
b100000000 '
b1101011 $
b1101011 )
b11111111 "
b11111111 (
#25800
0#
#26000
b1101011 +
b1101011 !
b1101011 *
b0 '
bz $
bz )
1%
0&
1#
#26100
b1010110 !
b1010110 *
b1010110 +
b1 '
b10001000 "
b10001000 (
#26200
b1100110 !
b1100110 *
b1100110 +
b10 '
b10101110 "
b10101110 (
#26300
b10010101 !
b10010101 *
b10010101 +
b11 '
b10011011 "
b10011011 (
#26400
b100 !
b100 *
b100 +
b100 '
b10010010 "
b10010010 (
#26500
b1101011 !
b1101011 *
b1101011 +
b101 '
b101000 "
b101000 (
#26600
b11001111 !
b11001111 *
b11001111 +
b110 '
b101101 "
b101101 (
#26700
b10001111 !
b10001111 *
b10001111 +
b111 '
b1001011 "
b1001011 (
#26800
b11001111 !
b11001111 *
b11001111 +
b1000 '
b11000010 "
b11000010 (
