finalProject/2_2/Encoder8x3.v
module Encoder8x3(output reg [2:0] code, input [7:0] data);
    always @(*) begin
        case(data)
            8'b0000_0001:  code = 3'd0;
            8'b0000_0010:  code = 3'd1;
            8'b0000_0100:  code = 3'd2;
            8'b0000_1000:  code = 3'd3;
            8'b0001_0000:  code = 3'd4;
            8'b0010_0000:  code = 3'd5;
            8'b0100_0000:  code = 3'd6;
            8'b1000_0000:  code = 3'd7;
            default:    code = 3'bx;
        endcase
    end 
endmodule

finalProject/2_2/tb_Encoder8x3.v
`timescale 10ns / 1ns 
`include "Encoder8x3.v"

module tb_Encoder8x3();
    reg [7:0] p_data;
    wire [2:0] p_code;

    Encoder8x3 enc(.data(p_data), .code(p_code));

    integer k;
    initial
    begin
        p_data = 8'b0;
        #10 p_data = 8'b1;
        for(k = 0; k < 8;k = k + 1)
            #10 p_data = p_data * 2;
    end

    initial
    begin
        $monitor($time, " code = %b, data = %b", p_code, p_data);
        $dumpfile("tb_Encoder8x3.vcd");
        $dumpvars(0, tb_Encoder8x3);
    end
endmodule

finalProject/2_2/tb_Encoder8x3.vcd
$date
	Thu Nov 21 21:39:42 2019
$end
$version
	Icarus Verilog
$end
$timescale
	1ns
$end
$scope module tb_Encoder8x3 $end
$var wire 3 ! p_code [2:0] $end
$var reg 8 " p_data [7:0] $end
$var integer 32 # k [31:0] $end
$scope module enc $end
$var wire 8 $ data [7:0] $end
$var reg 3 % code [2:0] $end
$upscope $end
$upscope $end
$enddefinitions $end
#0
$dumpvars
bx %
b0 $
bx #
b0 "
bx !
$end
#100
b0 !
b0 %
b0 #
b1 "
b1 $
#200
b1 !
b1 %
b1 #
b10 "
b10 $
#300
b10 !
b10 %
b10 #
b100 "
b100 $
#400
b11 !
b11 %
b11 #
b1000 "
b1000 $
#500
b100 !
b100 %
b100 #
b10000 "
b10000 $
#600
b101 !
b101 %
b101 #
b100000 "
b100000 $
#700
b110 !
b110 %
b110 #
b1000000 "
b1000000 $
#800
b111 !
b111 %
b111 #
b10000000 "
b10000000 $
#900
bx !
bx %
b1000 #
b0 "
b0 $
