dailyExercise/decoder3x8/decoder3x8_3.v
module decoder3x8( output [7:0] YL, input EN, C ,B ,A);
    wire [7:0] YH;
    assign  YH[7] = EN & ( C & B & A ),
            YH[6] = EN & ( C & B &~A ),
            YH[5] = EN & ( C &~B & A ),
            YH[4] = EN & ( C &~B &~A ),
            YH[3] = EN & (~C & B & A ),
            YH[2] = EN & (~C & B &~A ),
            YH[1] = EN & (~C &~B & A ),
            YH[0] = EN & (~C &~B &~A );

    assign YL = ~YH;
endmodule

dailyExercise/decoder3x8/top.v
`include "decoder3x8_3.v"
`timescale 1ns /100ps
// 3-8译码器
module top;
    reg [2:0] sel;
    wire [7:0] line;
    reg enable;

    initial
    begin
        #5 sel= 0;
        forever #5 sel = sel + 1;
    end

    decoder3x8 dec(line, enable, sel[2], sel[1], sel[0]);
    // decoder3x8 dec(line, enable, sel);

    initial 
    begin
        enable = 0;
        #3  enable = 1;
        #11 enable = 0;
        #12 enable = 1;
    end

    initial
        #60 $finish;
    
    initial
        $monitor($time, " en=%b, sel=%b, line=%b", enable, sel, line);

    initial
    begin
        $dumpfile("top.vcd");
        $dumpvars(0,top);
    end

endmodule

dailyExercise/decoder3x8/top.vcd
$date
	Mon Nov 18 16:03:22 2019
$end
$version
	Icarus Verilog
$end
$timescale
	100ps
$end
$scope module top $end
$var wire 8 ! line [7:0] $end
$var reg 1 " enable $end
$var reg 3 # sel [2:0] $end
$scope module dec $end
$var wire 1 $ A $end
$var wire 1 % B $end
$var wire 1 & C $end
$var wire 1 " EN $end
$var wire 8 ' YL [7:0] $end
$var wire 8 ( YH [7:0] $end
$upscope $end
$upscope $end
$enddefinitions $end
#0
$dumpvars
b0 (
b11111111 '
x&
x%
x$
bx #
0"
b11111111 !
$end
#30
bx !
bx '
bx (
1"
#50
b11111110 !
b11111110 '
b1 (
0&
0%
0$
b0 #
#100
b11111101 !
b11111101 '
b10 (
1$
b1 #
#140
b11111111 !
b11111111 '
b0 (
0"
#150
1%
0$
b10 #
#200
1$
b11 #
#250
1&
0%
0$
b100 #
#260
b11101111 !
b11101111 '
b10000 (
1"
#300
b11011111 !
b11011111 '
b100000 (
1$
b101 #
#350
b10111111 !
b10111111 '
b1000000 (
1%
0$
b110 #
#400
b1111111 !
b1111111 '
b10000000 (
1$
b111 #
#450
b11111110 !
b11111110 '
b1 (
0&
0%
0$
b0 #
#500
b11111101 !
b11111101 '
b10 (
1$
b1 #
#550
b11111011 !
b11111011 '
b100 (
1%
0$
b10 #
#600
b11110111 !
b11110111 '
b1000 (
1$
b11 #
