finalProject/2_5/comb_Y1.v
module comb_Y1(output Y, input A, B, C);
    assign  Y = 
            (~A & ~B &  C)|
            (~A &  B & ~C)|
            ( A & ~B & ~C)|
            ( A & ~B &  C);

endmodule

finalProject/2_5/tb_comb_Y1.v
`timescale 10ns / 1ns
`include "comb_Y1.v"
module tb_comb_Y1();
    reg p_A, p_B, p_C;
    wire p_Y;

    comb_Y1 comb(.Y(p_Y), .A(p_A), .B(p_B), .C(p_C));

    integer k;
    initial
    begin
        {p_A, p_B, p_C} = 3'bx;
        #10 {p_A, p_B, p_C} = 3'b000;
        for(k = 0; k < 8; k = k +1)
            #10 {p_A, p_B, p_C} = {p_A, p_B, p_C} + 3'b1;
        #10 $finish;
    end

    initial
    begin
        $monitor($time, " ABD = %b%b%b, Y=%b",
                        p_A, p_B, p_C, p_Y);
        $dumpfile("tb_comb_Y1.vcd");
        $dumpvars(0, tb_comb_Y1);
    end
endmodule

finalProject/2_5/tb_comb_Y1.vcd
$date
	Thu Nov 21 22:53:18 2019
$end
$version
	Icarus Verilog
$end
$timescale
	1ns
$end
$scope module tb_comb_Y1 $end
$var wire 1 ! p_Y $end
$var reg 1 " p_A $end
$var reg 1 # p_B $end
$var reg 1 $ p_C $end
$var integer 32 % k [31:0] $end
$scope module comb $end
$var wire 1 " A $end
$var wire 1 # B $end
$var wire 1 $ C $end
$var wire 1 ! Y $end
$upscope $end
$upscope $end
$enddefinitions $end
#0
$dumpvars
bx %
x$
x#
x"
x!
$end
#100
0!
b0 %
0"
0#
0$
#200
1!
b1 %
1$
#300
b10 %
1#
0$
#400
0!
b11 %
1$
#500
1!
b100 %
1"
0#
0$
#600
b101 %
1$
#700
0!
b110 %
1#
0$
#800
b111 %
1$
#900
b1000 %
0"
0#
0$
