finalProject/2_7/dec_counter.v
module dec_counter(output reg [3:0] count, input clk, reset);
    always @(posedge clk) begin
        if( reset )
            count = 4'b0;
        else if(count < 4'd9)
            count = count + 1'd1;
        else
            count = 4'b0;
    end
endmodule

finalProject/2_7/tb_dec_counter.v
`include "dec_counter.v"
`timescale 10ns / 1ns
module tb_dec_counter();
    reg p_clk;
    reg p_reset;
    wire [3:0] p_count;

    dec_counter counter(.count(p_count), .clk(p_clk), .reset(p_reset));

    initial
    begin
        p_clk = 1'b0;
        #5 p_clk = 1'b1;
        forever #5 p_clk = ~p_clk;
    end

    initial
    begin
        p_reset = 1'b1;
        #5 p_reset = 1'b0;
        #120 p_reset = 1'b1;
        #5  p_reset = 1'b0;
        #50 $finish;
    end

    initial
    begin
        $monitor($time, "count = %b", p_count);
        $dumpfile("tb_dec_counter.vcd");
        $dumpvars(0, tb_dec_counter);
    end
endmodule

finalProject/2_7/tb_dec_counter.vcd
$date
	Thu Nov 21 23:17:58 2019
$end
$version
	Icarus Verilog
$end
$timescale
	1ns
$end
$scope module tb_dec_counter $end
$var wire 4 ! p_count [3:0] $end
$var reg 1 " p_clk $end
$var reg 1 # p_reset $end
$scope module counter $end
$var wire 1 " clk $end
$var wire 1 # reset $end
$var reg 4 $ count [3:0] $end
$upscope $end
$upscope $end
$enddefinitions $end
#0
$dumpvars
bx $
1#
0"
bx !
$end
#50
b0 !
b0 $
0#
1"
#100
0"
#150
b1 !
b1 $
1"
#200
0"
#250
b10 !
b10 $
1"
#300
0"
#350
b11 !
b11 $
1"
#400
0"
#450
b100 !
b100 $
1"
#500
0"
#550
b101 !
b101 $
1"
#600
0"
#650
b110 !
b110 $
1"
#700
0"
#750
b111 !
b111 $
1"
#800
0"
#850
b1000 !
b1000 $
1"
#900
0"
#950
b1001 !
b1001 $
1"
#1000
0"
#1050
b0 !
b0 $
1"
#1100
0"
#1150
b1 !
b1 $
1"
#1200
0"
#1250
b0 !
b0 $
1"
1#
#1300
0"
0#
#1350
b1 !
b1 $
1"
#1400
0"
#1450
b10 !
b10 $
1"
#1500
0"
#1550
b11 !
b11 $
1"
#1600
0"
#1650
b100 !
b100 $
1"
#1700
0"
#1750
b101 !
b101 $
1"
