dailyExercise/filter/filter.v
module filter(output reg y, input clk, rst_n, din);
    reg [3:0] q;

    always @(posedge clk) begin
        if(!rst_n)
        begin
            q <= 4'b0;
            y <= 1'b0;
        end
        else
        begin
            if (&q[3:1])        y <= 1'b1;
            else if (~|q[3:1])  y <= 1'b0;

            q <= {q[2:0], din};
        end
    end 

endmodule

dailyExercise/filter/top.v
`include "filter.v"
`timescale 1ns / 100ps
// 移位寄存器数字滤波器
module top;
    wire p_y;
    reg p_clk, p_rst, p_d;

    filter flt(.y(p_y), .clk(p_clk), .rst_n(p_rst), .din(p_d));

    initial
    begin
        p_clk = 0;
        forever #5 p_clk = ~p_clk;
    end

    initial
    begin
        p_rst = 1'b0;
        #20 p_rst = 1'b1;
    end

    localparam N=40;
    reg [N-1:0] sig = 40'b1101_0010_0000_0111_1001_1111_0000_0001_1100_0010;
    integer k;
    initial 
    begin
        p_d = 1'b0;
        #30;
        for(k = 0; k < N; k = k + 1)
        begin
            #10 p_d = sig[N-1];
            sig = sig << 1;
        end
        $finish;
    end 

    initial
        $monitor($time, "rst = %b, din = %b, y = %b",
                        p_rst, p_d, p_y);

    initial
    begin 
        $dumpfile("top.vcd");
        $dumpvars(0, top);
    end

endmodule

dailyExercise/filter/top.vcd
$date
	Tue Nov 19 20:12:36 2019
$end
$version
	Icarus Verilog
$end
$timescale
	100ps
$end
$scope module top $end
$var wire 1 ! p_y $end
$var reg 1 " p_clk $end
$var reg 1 # p_d $end
$var reg 1 $ p_rst $end
$var reg 40 % sig [39:0] $end
$var integer 32 & k [31:0] $end
$scope module flt $end
$var wire 1 " clk $end
$var wire 1 # din $end
$var wire 1 $ rst_n $end
$var reg 4 ' q [3:0] $end
$var reg 1 ! y $end
$upscope $end
$upscope $end
$enddefinitions $end
#0
$dumpvars
bx '
bx &
b1101001000000111100111110000000111000010 %
0$
0#
0"
x!
$end
#50
0!
b0 '
1"
#100
0"
#150
1"
#200
0"
1$
#250
1"
#300
0"
b0 &
#350
1"
#400
0"
b1 &
b1010010000001111001111100000001110000100 %
1#
#450
b1 '
1"
#500
0"
b10 &
b100100000011110011111000000011100001000 %
#550
b11 '
1"
#600
0"
b11 &
b1001000000111100111110000000111000010000 %
0#
#650
b110 '
1"
#700
0"
b100 &
b10000001111001111100000001110000100000 %
1#
#750
b1101 '
1"
#800
0"
b101 &
b100000011110011111000000011100001000000 %
0#
#850
b1010 '
1"
#900
0"
b110 &
b1000000111100111110000000111000010000000 %
#950
b100 '
1"
#1000
0"
b111 &
b1111001111100000001110000100000000 %
1#
#1050
b1001 '
1"
#1100
0"
b1000 &
b11110011111000000011100001000000000 %
0#
#1150
b10 '
1"
#1200
0"
b1001 &
b111100111110000000111000010000000000 %
#1250
b100 '
1"
#1300
0"
b1010 &
b1111001111100000001110000100000000000 %
#1350
b1000 '
1"
#1400
0"
b1011 &
b11110011111000000011100001000000000000 %
#1450
b0 '
1"
#1500
0"
b1100 &
b111100111110000000111000010000000000000 %
#1550
1"
#1600
0"
b1101 &
b1111001111100000001110000100000000000000 %
#1650
1"
#1700
0"
b1110 &
b1110011111000000011100001000000000000000 %
1#
#1750
b1 '
1"
#1800
0"
b1111 &
b1100111110000000111000010000000000000000 %
#1850
b11 '
1"
#1900
0"
b10000 &
b1001111100000001110000100000000000000000 %
#1950
b111 '
1"
#2000
0"
b10001 &
b11111000000011100001000000000000000000 %
#2050
b1111 '
1"
#2100
0"
b10010 &
b111110000000111000010000000000000000000 %
0#
#2150
b1110 '
1!
1"
#2200
0"
b10011 &
b1111100000001110000100000000000000000000 %
#2250
b1100 '
1"
#2300
0"
b10100 &
b1111000000011100001000000000000000000000 %
1#
#2350
b1001 '
1"
#2400
0"
b10101 &
b1110000000111000010000000000000000000000 %
#2450
b11 '
1"
#2500
0"
b10110 &
b1100000001110000100000000000000000000000 %
#2550
b111 '
1"
#2600
0"
b10111 &
b1000000011100001000000000000000000000000 %
#2650
b1111 '
1"
#2700
0"
b11000 &
b111000010000000000000000000000000 %
#2750
1"
#2800
0"
b11001 &
b1110000100000000000000000000000000 %
0#
#2850
b1110 '
1"
#2900
0"
b11010 &
b11100001000000000000000000000000000 %
#2950
b1100 '
1"
#3000
0"
b11011 &
b111000010000000000000000000000000000 %
#3050
b1000 '
1"
#3100
0"
b11100 &
b1110000100000000000000000000000000000 %
#3150
b0 '
1"
#3200
0"
b11101 &
b11100001000000000000000000000000000000 %
#3250
0!
1"
#3300
0"
b11110 &
b111000010000000000000000000000000000000 %
#3350
1"
#3400
0"
b11111 &
b1110000100000000000000000000000000000000 %
#3450
1"
#3500
0"
b100000 &
b1100001000000000000000000000000000000000 %
1#
#3550
b1 '
1"
#3600
0"
b100001 &
b1000010000000000000000000000000000000000 %
#3650
b11 '
1"
#3700
0"
b100010 &
b100000000000000000000000000000000000 %
#3750
b111 '
1"
#3800
0"
b100011 &
b1000000000000000000000000000000000000 %
0#
#3850
b1110 '
1"
#3900
0"
b100100 &
b10000000000000000000000000000000000000 %
#3950
b1100 '
1!
1"
#4000
0"
b100101 &
b100000000000000000000000000000000000000 %
#4050
b1000 '
1"
#4100
0"
b100110 &
b1000000000000000000000000000000000000000 %
#4150
b0 '
1"
#4200
0"
b100111 &
b0 %
1#
#4250
b1 '
0!
1"
#4300
0"
b101000 &
0#
