dailyExercise/shiftreg/shiftreg_u.v
module shiftreg_u #(parameter N=4)( 
    output reg [N-1:0] q,
    input [N-1:0] d,
    input [1:0] s,
    input Lin, Rin,
    input clk,rst_n);

    always @(posedge clk) begin
        if(~rst_n)
            q <= 0;
        else
            case(s)
                2'b11:  q <= d;
                2'b10:  q <= {q[N-2:0], Rin};
                2'b01:  q <= {Lin, q[N-1:1]};
                default ;
            endcase
    end
endmodule

dailyExercise/shiftreg/top.v
`include "shiftreg_u.v"
`timescale 1ns / 100ps
// 移位寄存器
module top;
    reg p_clk;
    reg p_reset, p_set;
    reg [1:0] p_sel;
    reg p_in, p_lin, p_rin;
    wire [3:0] p_out;
    reg [3:0] p_pin;

    // shiftreg_ss shreg(.dout(p_out), .clk(p_clk), .reset(p_reset), .din(p_in));
    // shiftreg_sp shreg(.dout(p_out), .clk(p_clk), .reset(p_reset), .din(p_in));
    shiftreg_u sreg(.q(p_out), .d(p_pin), .s(p_sel), .Lin(p_lin), .Rin(p_rin), .clk(p_clk), .rst_n(p_reset));
    initial 
    begin
        p_clk = 1'b0;
        forever
            #5 p_clk = ~p_clk;  
    end

    initial 
    begin
        p_pin = 4'b0101;
        p_reset = 1'b0;
        #3 p_reset = 1'b1;
        #5 p_sel = 2'b11;
        #10 p_sel = 2'b10;
        forever 
            #10 p_sel = {$random} % 2 + 1;
    end
    
    initial
    begin
        p_lin = {$random}%2;
        p_rin = ~p_lin;
        forever
        begin
            #10;
            p_lin = {$random}%2;
            p_rin = ~p_lin;
        end
    end

    initial
        #180 $finish;
    
    initial
        $monitor($time, "sel = %b, dout = %b",
                        p_sel, p_out);
    
    initial 
    begin
        $dumpfile("top.vcd");
        $dumpvars(0, top);
    end
endmodule

dailyExercise/shiftreg/top.vcd
$date
	Tue Nov 19 19:52:32 2019
$end
$version
	Icarus Verilog
$end
$timescale
	100ps
$end
$scope module top $end
$var wire 4 ! p_out [3:0] $end
$var reg 1 " p_clk $end
$var reg 1 # p_lin $end
$var reg 4 $ p_pin [3:0] $end
$var reg 1 % p_reset $end
$var reg 1 & p_rin $end
$var reg 2 ' p_sel [1:0] $end
$scope module sreg $end
$var wire 1 # Lin $end
$var wire 1 & Rin $end
$var wire 1 " clk $end
$var wire 4 ( d [3:0] $end
$var wire 1 % rst_n $end
$var wire 2 ) s [1:0] $end
$var reg 4 * q [3:0] $end
$upscope $end
$upscope $end
$enddefinitions $end
#0
$dumpvars
bx *
bx )
b101 (
bx '
1&
0%
b101 $
0#
0"
bx !
$end
#30
1%
#50
1"
#80
b11 '
b11 )
#100
0"
0&
1#
#150
b101 !
b101 *
1"
#180
b10 '
b10 )
#200
0"
#250
b1010 !
b1010 *
1"
#300
0"
#350
b100 !
b100 *
1"
#400
0"
#450
b1000 !
b1000 *
1"
#480
b1 '
b1 )
#500
0"
#550
b1100 !
b1100 *
1"
#580
b10 '
b10 )
#600
0"
1&
0#
#650
b1001 !
b1001 *
1"
#700
0"
0&
1#
#750
b10 !
b10 *
1"
#780
b1 '
b1 )
#800
0"
#850
b1001 !
b1001 *
1"
#900
0"
#950
b1100 !
b1100 *
1"
#1000
0"
#1050
b1110 !
b1110 *
1"
#1080
b10 '
b10 )
#1100
0"
1&
0#
#1150
b1101 !
b1101 *
1"
#1200
0"
#1250
b1011 !
b1011 *
1"
#1280
b1 '
b1 )
#1300
0"
#1350
b101 !
b101 *
1"
#1380
b10 '
b10 )
#1400
0"
#1450
b1011 !
b1011 *
1"
#1500
0"
0&
1#
#1550
b110 !
b110 *
1"
#1600
0"
#1650
b1100 !
b1100 *
1"
#1680
b1 '
b1 )
#1700
0"
1&
0#
#1750
b110 !
b110 *
1"
