finalProject/2_10/filter_2.v
`include "DFF.v"
`include "JKFF.v"
module filter2(output sig_out, input sig_in, clock, reset);
    wire q0,q1,q2,q3;
    wire q1n,q2n,q3n;
    wire j,k;
    
    DFF ff0(.q(q0), .d(sig_in), .clk(clock), .rst_n(reset)),
        ff1(.q(q1), .d(q0),     .clk(clock), .rst_n(reset)),
        ff2(.q(q2), .d(q1),     .clk(clock), .rst_n(reset)),
        ff3(.q(q3), .d(q2),     .clk(clock), .rst_n(reset));
    
    not u10(q1n, q1),
        u11(q2n, q2),
        u12(q3n, q3);
    
    and u20(j, q1,  q2,  q3),
        u21(k, q1n, q2n, q3n);

    JKFF ff4(.q(sig_out), .j(j), .k(k), .clk(clock), .rst_n(reset));

endmodule

finalProject/2_10/filter.v

module filter(output reg sig_out, input sig_in, clock, reset);
    reg [3:0] buff;
    always @(posedge clock) begin
        if(!reset)
            buff <= 4'b0;
        else begin
            buff  <= buff << 1;
            buff[0] <= sig_in;
        end
    end
    always @(posedge clock) begin
        if( &buff[3:1] )
            sig_out <= 1'b1;
        else if ( ~|buff[3:1] )
            sig_out <= 1'b0; 
    end
endmodule

finalProject/2_10/tb_filter.v
`include "filter.v"
// `include "filter_2.v"

module tb_filter();
    wire p_sig_out;
    wire p_sig_out2;
    reg p_sig_in;
    reg p_clock;
    reg p_reset;
    reg [40:0] data;

    filter fil(.sig_out(p_sig_out), .sig_in(p_sig_in), .clock(p_clock), .reset(p_reset));
    // filter2 fil2(.sig_out(p_sig_out2), .sig_in(p_sig_in), .clock(p_clock), .reset(p_reset));

    integer k;
    initial
    begin
        data = 40'b1101_1000_0011_1101_1011_0000_1111_1111_0011_1110;
        p_sig_in = 1'bx;
        #20;
        for(k = 0; k < 40;k = k+1)
        begin
            #10;
            p_sig_in = data[40];
            data = data << 1;
        end
        #10 $finish;
    end

    initial
    begin
        p_reset = 1'b0;
        #15 p_reset = 1'b1;
    end

    initial
    begin   
        p_clock = 1'b0;
        forever #5 p_clock = ~p_clock;
    end

    initial
    begin
        $monitor($time, " reset=%b, sig_in=%b, sig_out=%b",//%b",
                        p_reset, p_sig_in, p_sig_out);//, p_sig_out2);
        $dumpfile("tb_filter.vcd");
        $dumpvars(0, tb_filter);
    end
endmodule

finalProject/2_10/tb_filter.vcd
$date
	Sun Nov 24 09:19:57 2019
$end
$version
	Icarus Verilog
$end
$timescale
	1s
$end
$scope module tb_filter $end
$var wire 1 ! p_sig_out $end
$var reg 41 " data [40:0] $end
$var reg 1 # p_clock $end
$var reg 1 $ p_reset $end
$var reg 1 % p_sig_in $end
$var integer 32 & k [31:0] $end
$scope module fil $end
$var wire 1 # clock $end
$var wire 1 $ reset $end
$var wire 1 % sig_in $end
$var reg 4 ' buff [3:0] $end
$var reg 1 ! sig_out $end
$upscope $end
$upscope $end
$enddefinitions $end
#0
$dumpvars
bx '
bx &
x%
0$
0#
b1101100000111101101100001111111100111110 "
x!
$end
#5
b0 '
1#
#10
0#
#15
0!
b0x '
1#
1$
#20
0#
b0 &
#25
b0xx '
1#
#30
0#
b1 &
b11011000001111011011000011111111001111100 "
0%
#35
b0xx0 '
1#
#40
0#
b10 &
b10110000011110110110000111111110011111000 "
1%
#45
bx01 '
1#
#50
0#
b11 &
b1100000111101101100001111111100111110000 "
#55
bx011 '
1#
#60
0#
b100 &
b11000001111011011000011111111001111100000 "
0%
#65
b110 '
1#
#70
0#
b101 &
b10000011110110110000111111110011111000000 "
1%
#75
b1101 '
1#
#80
0#
b110 &
b111101101100001111111100111110000000 "
#85
b1011 '
1#
#90
0#
b111 &
b1111011011000011111111001111100000000 "
0%
#95
b110 '
1#
#100
0#
b1000 &
b11110110110000111111110011111000000000 "
#105
b1100 '
1#
#110
0#
b1001 &
b111101101100001111111100111110000000000 "
#115
b1000 '
1#
#120
0#
b1010 &
b1111011011000011111111001111100000000000 "
#125
b0 '
1#
#130
0#
b1011 &
b11110110110000111111110011111000000000000 "
#135
1#
#140
0#
b1100 &
b11101101100001111111100111110000000000000 "
1%
#145
b1 '
1#
#150
0#
b1101 &
b11011011000011111111001111100000000000000 "
#155
b11 '
1#
#160
0#
b1110 &
b10110110000111111110011111000000000000000 "
#165
b111 '
1#
#170
0#
b1111 &
b1101100001111111100111110000000000000000 "
#175
b1111 '
1#
#180
0#
b10000 &
b11011000011111111001111100000000000000000 "
0%
#185
b1110 '
1!
1#
#190
0#
b10001 &
b10110000111111110011111000000000000000000 "
1%
#195
b1101 '
1#
#200
0#
b10010 &
b1100001111111100111110000000000000000000 "
#205
b1011 '
1#
#210
0#
b10011 &
b11000011111111001111100000000000000000000 "
0%
#215
b110 '
1#
#220
0#
b10100 &
b10000111111110011111000000000000000000000 "
1%
#225
b1101 '
1#
#230
0#
b10101 &
b1111111100111110000000000000000000000 "
#235
b1011 '
1#
#240
0#
b10110 &
b11111111001111100000000000000000000000 "
0%
#245
b110 '
1#
#250
0#
b10111 &
b111111110011111000000000000000000000000 "
#255
b1100 '
1#
#260
0#
b11000 &
b1111111100111110000000000000000000000000 "
#265
b1000 '
1#
#270
0#
b11001 &
b11111111001111100000000000000000000000000 "
#275
b0 '
1#
#280
0#
b11010 &
b11111110011111000000000000000000000000000 "
1%
#285
b1 '
0!
1#
#290
0#
b11011 &
b11111100111110000000000000000000000000000 "
#295
b11 '
1#
#300
0#
b11100 &
b11111001111100000000000000000000000000000 "
#305
b111 '
1#
#310
0#
b11101 &
b11110011111000000000000000000000000000000 "
#315
b1111 '
1#
#320
0#
b11110 &
b11100111110000000000000000000000000000000 "
#325
b1111 '
1!
1#
#330
0#
b11111 &
b11001111100000000000000000000000000000000 "
#335
b1111 '
1#
#340
0#
b100000 &
b10011111000000000000000000000000000000000 "
#345
b1111 '
1#
#350
0#
b100001 &
b111110000000000000000000000000000000000 "
#355
b1111 '
1#
#360
0#
b100010 &
b1111100000000000000000000000000000000000 "
0%
#365
b1110 '
1#
#370
0#
b100011 &
b11111000000000000000000000000000000000000 "
#375
b1100 '
1#
#380
0#
b100100 &
b11110000000000000000000000000000000000000 "
1%
#385
b1001 '
1#
#390
0#
b100101 &
b11100000000000000000000000000000000000000 "
#395
b11 '
1#
#400
0#
b100110 &
b11000000000000000000000000000000000000000 "
#405
b111 '
1#
#410
0#
b100111 &
b10000000000000000000000000000000000000000 "
#415
b1111 '
1#
#420
0#
b101000 &
b0 "
#425
b1111 '
1#
