finalProject/2_1/wavegen.v
`timescale 10ns / 1ns
module wavegen(output reg sig);
    always begin
        sig <= 1'b0;
        #2  sig <= 1'b1;
        #1  sig <= 1'b0;
        #9  sig <= 1'b1;
        #10 sig <= 1'b0;
        #2  sig <= 1'b1;
        #3  sig <= 1'b0;
        #5  sig <= 1'b1;
    end
    
endmodule

finalProject/2_1/wavegen.vcd
$date
	Thu Nov 21 21:29:16 2019
$end
$version
	Icarus Verilog
$end
$timescale
	1ns
$end
$scope module wavegen $end
$var reg 1 ! sig $end
$upscope $end
$enddefinitions $end
#0
$dumpvars
0!
$end
#20
1!
#30
0!
#120
1!
#220
0!
#240
1!
#270
0!
#320
1!
